blockfirates/__init__.py
blockfirates/client.py
BlockFiRates-0.5.0.dist-info/METADATA
BlockFiRates-0.5.0.dist-info/WHEEL
BlockFiRates-0.5.0.dist-info/top_level.txt
BlockFiRates-0.5.0.dist-info/RECORD
