Metadata-Version: 2.1
Name: BlockFiRates
Version: 0.5.0
Home-page: https://github.com/pgoslatara/blockfirates
Author: P. G. Ó'Slatara
Author-email: pgoslatara@gmail.com
License: MIT
Keywords: crypto,python3,blockfi
Classifier: Environment :: Console
Classifier: Framework :: Flake8
Classifier: Programming Language :: Python :: 3.7
Classifier: Programming Language :: Python :: 3.8
Classifier: Programming Language :: Python :: 3.9
Classifier: Programming Language :: Python :: 3.10
Requires-Python: >=3.7.*,<=3.10.*
Requires-Dist: cloudscraper (==1.2.60)
Provides-Extra: dev
Requires-Dist: build (==0.8.0) ; extra == 'dev'
Requires-Dist: pre-commit (==2.19.0) ; extra == 'dev'
Requires-Dist: setuptools (==62.3.4) ; extra == 'dev'
Requires-Dist: twine (==4.0.1) ; extra == 'dev'
Requires-Dist: pytest (==7.1.2) ; extra == 'dev'
